yui/__init__.py
yui/images.qrc
yui/images_rc.py
yui/img.py
yui/qrc_tools.py
yui/wdg.py
yui/ydict.py
yui/yfield.py
yui/yform.py
yui/ylookup.py
yui/ymodel.py
yui/ystat.py
yui/ytable.py
yui/ytree.py
yus/__init__.py
yus/dbm.py
yut/__init__.py
yut/asynx.py
yut/mes.py
yut/rmi.py
yut/win32.py
yut-0.2.16.dist-info/METADATA
yut-0.2.16.dist-info/WHEEL
yut-0.2.16.dist-info/RECORD
