Metadata-Version: 2.4
Name: yut
Version: 0.2.16
Summary: 轻量级GUI应用系统框架库，基于(Qt)PySide编写的通用表单、列表、统计组件以及SqlAlchemy扩展的数据库组件。利用SqlAlchemy反射机制构建数据集，前后端使用统一的数据字段定义，在业务级别动态决定数据项的输入和展示方式，并允许开发者进一步控制细节。后端生成的数据集封装为Pandas Dataframe传递给GUI，作为Model/View机制的基础，并在此基础上实现通用统计功能，包括分组统计、交叉统计，绘制相应的统计图表。
Author: tjy
Author-email: tjy@yeah.net
Requires-Python: >=3.12
Classifier: Programming Language :: Python :: 3
Classifier: Programming Language :: Python :: 3.12
Classifier: Programming Language :: Python :: 3.13
Classifier: Programming Language :: Python :: 3.14
Project-URL: Homepage, https://gitee.com/jy_tao/yut
